watson/__init__.py
watson/http/__init__.py
watson/http/cookies.py
watson/http/headers.py
watson/http/messages.py
watson/http/uri.py
watson/http/wsgi.py
watson/http/sessions/__init__.py
watson/http/sessions/abc.py
watson/http/sessions/file.py
watson/http/sessions/memcache.py
watson/http/sessions/memory.py
watson/http/sessions/redis.py
watson/http/sessions/serializers.py
watson_http-1.2.6.dist-info/AUTHORS
watson_http-1.2.6.dist-info/LICENSE
watson_http-1.2.6.dist-info/METADATA
watson_http-1.2.6.dist-info/WHEEL
watson_http-1.2.6.dist-info/top_level.txt
watson_http-1.2.6.dist-info/RECORD
