Metadata-Version: 2.1
Name: watson-http
Version: 1.2.6
Summary: Work with HTTP Request/Response objects, sessions, and more.
Home-page: http://github.com/watsonpy/watson-http
Author: Simon Coulton
Author-email: simon@bespohk.com
License: Copyright (c) Bespohk and individual contributors.
Requires-Dist: watson-common (>=1.1.2)
Provides-Extra: test
Requires-Dist: pytest ; extra == 'test'
Requires-Dist: pytest-cov ; extra == 'test'
Requires-Dist: coverage ; extra == 'test'
Requires-Dist: coveralls ; extra == 'test'
